vt/__init__.py
vt/client/__init__.py
vt/env/__init__.py
vt_restful-0.0.11.dist-info/LICENSE
vt_restful-0.0.11.dist-info/METADATA
vt_restful-0.0.11.dist-info/WHEEL
vt_restful-0.0.11.dist-info/RECORD
